<?xml version="1.0"?>
<API_Reply System="ABG" Version="1.0" Product="General" Customer="A" Session="379895136" RequestCode="7" Result="OK">
  <Agent>YourABTANumber</Agent>
  <Booking>
    <BookingRef>YourBookingRef</BookingRef>
    <Amendable>Y</Amendable>
    <BookingDate>2018-02-09</BookingDate>
    <CanxDate/>
    <VoucherRef>YourVoucherRef</VoucherRef>
    <Brand>HX</Brand>
    <Domain/>
    <Lang/>
    <Platform/>
    <AgentComm>11.42</AgentComm>
    <VATonComm>1.82</VATonComm>
    <MidocoBasket/>
    <MidocoCustRef/>
    <MidocoId/>
  </Booking>
  <Itinerary>
    <Product>Hotel</Product>
    <ArrivalDate>2018-12-01</ArrivalDate>
    <LastAmendDate/>
    <Remarks/>
    <BoardBasis>F</BoardBasis>
    <HotelCode>MUCLAN</HotelCode>
    <Nights>1</Nights>
    <NonSmoking>Y</NonSmoking>
    <FlightNum/>
    <Code>MUCLAN</Code>
    <Name>Schweigers Landgasthof</Name>
  </Itinerary>
  <ClientDetails>
    <Title>HERR</Title>
    <Initial>T</Initial>
    <Surname>TEST</Surname>
    <Address>TBC</Address>
    <Address>TBC</Address>
    <Address/>
    <Town>TESTVILLE</Town>
    <County>TESTSHIRE</County>
    <Postcode>TE1 STS</Postcode>
    <DayPhone>01234567890</DayPhone>
    <EvePhone>01234567890</EvePhone>
    <Email>test@test.com</Email>
    <DataProtection/>
    <CustInvReqd>N</CustInvReqd>
    <SecEmail/>
  </ClientDetails>
  <Pricing>
    <AmountPaid>120.00</AmountPaid>
    <AmountDue>0.00</AmountDue>
    <Refund/>
    <BasePrice>120.00</BasePrice>
  </Pricing>
  <CarDetails>
    <Registration>-</Registration>
    <Make>-</Make>
    <Model>-</Model>
    <Colour>-</Colour>
    <OutTerm>MUC</OutTerm>
    <RetTerm/>
    <OutFltNo/>
    <RetFltNo/>
    <Mobile/>
    <Pax>2</Pax>
    <OutFltTime/>
    <InFltTime/>
    <Ship/>
    <Pier/>
    <ChildSeat/>
    <AddlServices/>
    <ParkingDays/>
    <ParkingSpaces/>
    <CarArrTime>0030</CarArrTime>
    <CarDetFlags/>
    <CarDepTime>2330</CarDepTime>
  </CarDetails>
  <Room>
    <RoomCode>DZ</RoomCode>
    <Rooms>1</Rooms>
    <Adults>2</Adults>
    <Children>0</Children>
    <Infants>0</Infants>
  </Room>
  <CurrentSupplements/>
  <SepaEncashment/>
  <SepaID/>
  <CustRef/>
  <API_Header>
    <Request>
      <ABTANumber>YourABTANumber</ABTANumber>
      <Password>YourPassword</Password>
      <key>YourKey</key>
      <Email>test@test.com</Email>
      <System>ABG</System>
      <v>1</v>
      <lang>de</lang>
    </Request>
  </API_Header>
</API_Reply>
